ovos_skill_pyradios/LICENSE
ovos_skill_pyradios/MANIFEST.in
ovos_skill_pyradios/README.md
ovos_skill_pyradios/__init__.py
ovos_skill_pyradios/requirements.txt
ovos_skill_pyradios/version.py
ovos_skill_pyradios/locale/ca-es/pyradios.voc
ovos_skill_pyradios/locale/ca-es/radio.voc
ovos_skill_pyradios/locale/cs-cz/pyradios.voc
ovos_skill_pyradios/locale/cs-cz/radio.voc
ovos_skill_pyradios/locale/da-dk/pyradios.voc
ovos_skill_pyradios/locale/da-dk/radio.voc
ovos_skill_pyradios/locale/de-de/pyradios.voc
ovos_skill_pyradios/locale/de-de/radio.voc
ovos_skill_pyradios/locale/en-us/pyradios.voc
ovos_skill_pyradios/locale/en-us/radio.voc
ovos_skill_pyradios/locale/en-us/skill.json
ovos_skill_pyradios/locale/es-es/pyradios.voc
ovos_skill_pyradios/locale/es-es/radio.voc
ovos_skill_pyradios/locale/eu/radio.voc
ovos_skill_pyradios/locale/fr-fr/pyradios.voc
ovos_skill_pyradios/locale/fr-fr/radio.voc
ovos_skill_pyradios/locale/hu-hu/pyradios.voc
ovos_skill_pyradios/locale/hu-hu/radio.voc
ovos_skill_pyradios/locale/it-it/pyradios.voc
ovos_skill_pyradios/locale/it-it/radio.voc
ovos_skill_pyradios/locale/nl-nl/pyradios.voc
ovos_skill_pyradios/locale/nl-nl/radio.voc
ovos_skill_pyradios/locale/pl-pl/pyradios.voc
ovos_skill_pyradios/locale/pl-pl/radio.voc
ovos_skill_pyradios/locale/pt-pt/pyradios.voc
ovos_skill_pyradios/locale/pt-pt/radio.voc
ovos_skill_pyradios/locale/ru-ru/pyradios.voc
ovos_skill_pyradios/locale/ru-ru/radio.voc
ovos_skill_pyradios/locale/sv-fi/pyradios.voc
ovos_skill_pyradios/locale/sv-fi/radio.voc
ovos_skill_pyradios/locale/sv-se/pyradios.voc
ovos_skill_pyradios/locale/sv-se/radio.voc
ovos_skill_pyradios/ovos_skill_pyradios.egg-info/PKG-INFO
ovos_skill_pyradios/ovos_skill_pyradios.egg-info/SOURCES.txt
ovos_skill_pyradios/ovos_skill_pyradios.egg-info/dependency_links.txt
ovos_skill_pyradios/ovos_skill_pyradios.egg-info/entry_points.txt
ovos_skill_pyradios/ovos_skill_pyradios.egg-info/requires.txt
ovos_skill_pyradios/ovos_skill_pyradios.egg-info/top_level.txt
ovos_skill_pyradios/res/radio-tuner-small.png
ovos_skill_pyradios/res/radio-tuner.png
ovos_skill_pyradios/res/radio-tuner.svg
ovos_skill_pyradios-0.1.5.dist-info/LICENSE
ovos_skill_pyradios-0.1.5.dist-info/METADATA
ovos_skill_pyradios-0.1.5.dist-info/WHEEL
ovos_skill_pyradios-0.1.5.dist-info/entry_points.txt
ovos_skill_pyradios-0.1.5.dist-info/top_level.txt
ovos_skill_pyradios-0.1.5.dist-info/RECORD
