Metadata-Version: 2.1
Name: ovos-skill-pyradios
Version: 0.1.5
Summary: ovos pyradios skill plugin
Home-page: https://github.com/OpenVoiceOS/ovos-skill-pyradios
Author: Flávio De Melo
Author-email: flavio.eler@gmail.com
License: Apache-2.0
Keywords: ovos skill plugin
License-File: LICENSE
Requires-Dist: ovos-utils>=0.1.0
Requires-Dist: ovos-bus-client>=0.0.9
Requires-Dist: ovos-workshop<8.0.0,>=0.0.16
Requires-Dist: pyradios
Requires-Dist: dead-simple-cache>=1.2.2
Requires-Dist: rapidfuzz
